altcos.py
altcos_common-2.0.0.dist-info/LICENSE
altcos_common-2.0.0.dist-info/METADATA
altcos_common-2.0.0.dist-info/WHEEL
altcos_common-2.0.0.dist-info/top_level.txt
altcos_common-2.0.0.dist-info/RECORD
