Metadata-Version: 2.1
Name: altcos-common
Version: 2.0.0
Summary: Components for working with altcos
Author-email: Ivan Pepelyaev <fl0pp5@altlinux.org>
Project-URL: Homepage, https://github.com/fl0pp5/altcos-common
Classifier: Programming Language :: Python :: 3
Classifier: Operating System :: POSIX :: Linux
Classifier: License :: OSI Approved :: MIT License
Requires-Python: >=3.10
License-File: LICENSE
Requires-Dist: pygobject
